pg_schema_toolkit/__init__.py
pg_schema_toolkit/cli.py
pg_schema_toolkit/scripts/__init__.py
pg_schema_toolkit/scripts/audit_generator.py
pg_schema_toolkit/scripts/change_generator.py
pg_schema_toolkit/scripts/db_config.py
pg_schema_toolkit/scripts/ddl_generator.py
pg_schema_toolkit/scripts/differ.py
pg_schema_toolkit/scripts/introspector.py
pg_schema_toolkit/scripts/schema_loader.py
pg_schema_toolkit-0.1.1.dist-info/licenses/LICENSE
pg_schema_toolkit-0.1.1.dist-info/METADATA
pg_schema_toolkit-0.1.1.dist-info/WHEEL
pg_schema_toolkit-0.1.1.dist-info/entry_points.txt
pg_schema_toolkit-0.1.1.dist-info/top_level.txt
pg_schema_toolkit-0.1.1.dist-info/RECORD
