Metadata-Version: 2.4
Name: pg-schema-toolkit
Version: 0.1.1
Summary: PostgreSQL schema management toolkit with YAML-based definitions
Author: fyin
License: MIT
Project-URL: Repository, https://github.com/fuchangyin/pg-schema-toolkit
Keywords: postgresql,database,schema,migration,ddl
Classifier: Development Status :: 4 - Beta
Classifier: Intended Audience :: Developers
Classifier: License :: OSI Approved :: MIT License
Classifier: Programming Language :: Python :: 3
Classifier: Programming Language :: Python :: 3.8
Classifier: Programming Language :: Python :: 3.9
Classifier: Programming Language :: Python :: 3.10
Classifier: Programming Language :: Python :: 3.11
Classifier: Programming Language :: Python :: 3.12
Classifier: Topic :: Database
Classifier: Topic :: Software Development :: Libraries :: Python Modules
Requires-Python: >=3.8
License-File: LICENSE
Requires-Dist: psycopg2-binary>=2.9.0
Requires-Dist: PyYAML>=6.0
Provides-Extra: completion
Requires-Dist: argcomplete>=2.0.0; extra == "completion"
Provides-Extra: dev
Requires-Dist: pytest>=7.0.0; extra == "dev"
Requires-Dist: pytest-cov>=4.0.0; extra == "dev"
Requires-Dist: black>=23.0.0; extra == "dev"
Requires-Dist: flake8>=6.0.0; extra == "dev"
Requires-Dist: mypy>=1.0.0; extra == "dev"
Requires-Dist: argcomplete>=2.0.0; extra == "dev"
Dynamic: license-file
